README.rst
setup.py
rpi_lcd/__init__.py
rpi_lcd.egg-info/PKG-INFO
rpi_lcd.egg-info/SOURCES.txt
rpi_lcd.egg-info/dependency_links.txt
rpi_lcd.egg-info/not-zip-safe
rpi_lcd.egg-info/requires.txt
rpi_lcd.egg-info/top_level.txt