Metadata-Version: 1.1
Name: rpi-lcd
Version: 0.0.3
Summary: I²C LCD library for RaspberryPi
Home-page: https://github.com/bogdal/rpi-lcd
Author: Adam Bogdał
Author-email: adam@bogdal.pl
License: UNKNOWN
Platform: UNKNOWN
Classifier: Intended Audience :: Developers
Classifier: License :: OSI Approved :: MIT License
Classifier: Operating System :: OS Independent
Classifier: Programming Language :: Python
Classifier: Programming Language :: Python :: 2
Classifier: Programming Language :: Python :: 3
Classifier: Topic :: Software Development :: Libraries :: Python Modules
Classifier: Topic :: System :: Hardware :: Hardware Drivers
